{
  "reportTitle": "reader-e2e",
  "stats": {
    "suites": 1,
    "tests": 2,
    "passes": 2,
    "pending": 0,
    "failures": 0,
    "start": "2016-05-04T07:21:18.109Z",
    "end": "2016-05-04T07:21:47.772Z",
    "duration": 29663,
    "testsRegistered": 2,
    "passPercent": 100,
    "pendingPercent": 0,
    "other": 0,
    "hasOther": false,
    "skipped": 0,
    "hasSkipped": false,
    "passPercentClass": "success",
    "pendingPercentClass": "danger"
  },
  "suites": {
    "title": "",
    "suites": [
      {
        "title": "DLS - Login Page",
        "suites": [],
        "tests": [
          {
            "title": "Test Login page with incorrect credentials",
            "fullTitle": "DLS - Login Page Test Login page with incorrect credentials",
            "timedOut": false,
            "duration": 14946,
            "state": "passed",
            "speed": "slow",
            "pass": true,
            "fail": false,
            "pending": false,
            "code": "<span class=\"hljs-keyword\">var</span> readerHome = client.page.LoginPage();<br>readerHome.navigate(client.launch_url);<br>readerHome.login(<span class=\"hljs-string\">'qa8'</span>,<span class=\"hljs-string\">'admin1'</span>,<span class=\"hljs-string\">'Compro11'</span>);<br>readerHome.expect.element(<span class=\"hljs-string\">'@credentialsAlert'</span>).text.to.equal(<span class=\"hljs-string\">'Invalid Credentials'</span>);<br>client.end();",
            "isRoot": false,
            "uuid": "b8a70fc4-0303-4730-a72b-39be56c9d230",
            "parentUUID": "eb32a3ea-d0bc-4d34-a3ef-3c2da13de6d8",
            "skipped": false
          },
          {
            "title": "Test Login page with correct credentials",
            "fullTitle": "DLS - Login Page Test Login page with correct credentials",
            "timedOut": false,
            "duration": 14707,
            "state": "passed",
            "speed": "slow",
            "pass": true,
            "fail": false,
            "pending": false,
            "code": "<span class=\"hljs-keyword\">var</span> readerHome = client.page.LoginPage();<br>readerHome.navigate(client.launch_url);<br>readerHome.login(<span class=\"hljs-string\">'qa8'</span>,<span class=\"hljs-string\">'admin'</span>,<span class=\"hljs-string\">'Compro11'</span>);<br><span class=\"hljs-keyword\">var</span> readerDashboard = client.page.DashboardPage();<br>readerDashboard.expect.element(<span class=\"hljs-string\">'@bookThumbnail'</span>).to.be.present.after(<span class=\"hljs-number\">10000</span>);<br>client.end();",
            "isRoot": false,
            "uuid": "d57ac8f5-4e20-41ab-b6dd-277c34c5bb4b",
            "parentUUID": "eb32a3ea-d0bc-4d34-a3ef-3c2da13de6d8",
            "skipped": false
          }
        ],
        "pending": [],
        "root": false,
        "_timeout": 20000,
        "file": "/tests/e2e/specs/LoginTest",
        "uuid": "eb32a3ea-d0bc-4d34-a3ef-3c2da13de6d8",
        "fullFile": "/home/travis/build/comprodls/reader-e2e/tests/e2e/specs/LoginTest",
        "passes": [
          {
            "title": "Test Login page with incorrect credentials",
            "fullTitle": "DLS - Login Page Test Login page with incorrect credentials",
            "timedOut": false,
            "duration": 14946,
            "state": "passed",
            "speed": "slow",
            "pass": true,
            "fail": false,
            "pending": false,
            "code": "<span class=\"hljs-keyword\">var</span> readerHome = client.page.LoginPage();<br>readerHome.navigate(client.launch_url);<br>readerHome.login(<span class=\"hljs-string\">'qa8'</span>,<span class=\"hljs-string\">'admin1'</span>,<span class=\"hljs-string\">'Compro11'</span>);<br>readerHome.expect.element(<span class=\"hljs-string\">'@credentialsAlert'</span>).text.to.equal(<span class=\"hljs-string\">'Invalid Credentials'</span>);<br>client.end();",
            "isRoot": false,
            "uuid": "b8a70fc4-0303-4730-a72b-39be56c9d230",
            "parentUUID": "eb32a3ea-d0bc-4d34-a3ef-3c2da13de6d8",
            "skipped": false
          },
          {
            "title": "Test Login page with correct credentials",
            "fullTitle": "DLS - Login Page Test Login page with correct credentials",
            "timedOut": false,
            "duration": 14707,
            "state": "passed",
            "speed": "slow",
            "pass": true,
            "fail": false,
            "pending": false,
            "code": "<span class=\"hljs-keyword\">var</span> readerHome = client.page.LoginPage();<br>readerHome.navigate(client.launch_url);<br>readerHome.login(<span class=\"hljs-string\">'qa8'</span>,<span class=\"hljs-string\">'admin'</span>,<span class=\"hljs-string\">'Compro11'</span>);<br><span class=\"hljs-keyword\">var</span> readerDashboard = client.page.DashboardPage();<br>readerDashboard.expect.element(<span class=\"hljs-string\">'@bookThumbnail'</span>).to.be.present.after(<span class=\"hljs-number\">10000</span>);<br>client.end();",
            "isRoot": false,
            "uuid": "d57ac8f5-4e20-41ab-b6dd-277c34c5bb4b",
            "parentUUID": "eb32a3ea-d0bc-4d34-a3ef-3c2da13de6d8",
            "skipped": false
          }
        ],
        "failures": [],
        "skipped": [],
        "hasTests": true,
        "hasSuites": false,
        "totalTests": 2,
        "totalPasses": 2,
        "totalFailures": 0,
        "totalPending": 0,
        "totalSkipped": 0,
        "hasPasses": true,
        "hasFailures": false,
        "hasPending": false,
        "hasSkipped": false,
        "duration": 29653
      }
    ],
    "tests": [],
    "pending": [],
    "root": true,
    "_timeout": 20000,
    "uuid": "324db6dc-c786-4270-b193-348dcb5c88ee",
    "fullFile": "",
    "file": "",
    "passes": [],
    "failures": [],
    "skipped": [],
    "hasTests": false,
    "hasSuites": true,
    "totalTests": 0,
    "totalPasses": 0,
    "totalFailures": 0,
    "totalPending": 0,
    "totalSkipped": 0,
    "hasPasses": false,
    "hasFailures": false,
    "hasPending": false,
    "hasSkipped": false,
    "duration": 0,
    "rootEmpty": true
  },
  "allTests": [
    {
      "title": "Test Login page with incorrect credentials",
      "fullTitle": "DLS - Login Page Test Login page with incorrect credentials",
      "timedOut": false,
      "duration": 14946,
      "state": "passed",
      "speed": "slow",
      "pass": true,
      "fail": false,
      "pending": false,
      "code": "<span class=\"hljs-keyword\">var</span> readerHome = client.page.LoginPage();<br>readerHome.navigate(client.launch_url);<br>readerHome.login(<span class=\"hljs-string\">'qa8'</span>,<span class=\"hljs-string\">'admin1'</span>,<span class=\"hljs-string\">'Compro11'</span>);<br>readerHome.expect.element(<span class=\"hljs-string\">'@credentialsAlert'</span>).text.to.equal(<span class=\"hljs-string\">'Invalid Credentials'</span>);<br>client.end();",
      "isRoot": false,
      "uuid": "89aa451c-da50-4c9f-a52a-eebec3e3d38d",
      "parentUUID": "eb32a3ea-d0bc-4d34-a3ef-3c2da13de6d8",
      "skipped": false
    },
    {
      "title": "Test Login page with correct credentials",
      "fullTitle": "DLS - Login Page Test Login page with correct credentials",
      "timedOut": false,
      "duration": 14707,
      "state": "passed",
      "speed": "slow",
      "pass": true,
      "fail": false,
      "pending": false,
      "code": "<span class=\"hljs-keyword\">var</span> readerHome = client.page.LoginPage();<br>readerHome.navigate(client.launch_url);<br>readerHome.login(<span class=\"hljs-string\">'qa8'</span>,<span class=\"hljs-string\">'admin'</span>,<span class=\"hljs-string\">'Compro11'</span>);<br><span class=\"hljs-keyword\">var</span> readerDashboard = client.page.DashboardPage();<br>readerDashboard.expect.element(<span class=\"hljs-string\">'@bookThumbnail'</span>).to.be.present.after(<span class=\"hljs-number\">10000</span>);<br>client.end();",
      "isRoot": false,
      "uuid": "aaef978a-0f54-4c13-99c0-b3363417f1f7",
      "parentUUID": "eb32a3ea-d0bc-4d34-a3ef-3c2da13de6d8",
      "skipped": false
    }
  ],
  "allPending": [],
  "allPasses": [
    {
      "title": "Test Login page with incorrect credentials",
      "fullTitle": "DLS - Login Page Test Login page with incorrect credentials",
      "timedOut": false,
      "duration": 14946,
      "state": "passed",
      "speed": "slow",
      "pass": true,
      "fail": false,
      "pending": false,
      "code": "<span class=\"hljs-keyword\">var</span> readerHome = client.page.LoginPage();<br>readerHome.navigate(client.launch_url);<br>readerHome.login(<span class=\"hljs-string\">'qa8'</span>,<span class=\"hljs-string\">'admin1'</span>,<span class=\"hljs-string\">'Compro11'</span>);<br>readerHome.expect.element(<span class=\"hljs-string\">'@credentialsAlert'</span>).text.to.equal(<span class=\"hljs-string\">'Invalid Credentials'</span>);<br>client.end();",
      "isRoot": false,
      "uuid": "24dd1dfb-8991-490a-b5d5-2d6984552d1c",
      "parentUUID": "eb32a3ea-d0bc-4d34-a3ef-3c2da13de6d8",
      "skipped": false
    },
    {
      "title": "Test Login page with correct credentials",
      "fullTitle": "DLS - Login Page Test Login page with correct credentials",
      "timedOut": false,
      "duration": 14707,
      "state": "passed",
      "speed": "slow",
      "pass": true,
      "fail": false,
      "pending": false,
      "code": "<span class=\"hljs-keyword\">var</span> readerHome = client.page.LoginPage();<br>readerHome.navigate(client.launch_url);<br>readerHome.login(<span class=\"hljs-string\">'qa8'</span>,<span class=\"hljs-string\">'admin'</span>,<span class=\"hljs-string\">'Compro11'</span>);<br><span class=\"hljs-keyword\">var</span> readerDashboard = client.page.DashboardPage();<br>readerDashboard.expect.element(<span class=\"hljs-string\">'@bookThumbnail'</span>).to.be.present.after(<span class=\"hljs-number\">10000</span>);<br>client.end();",
      "isRoot": false,
      "uuid": "a4a19ca0-4928-4f51-bd5b-9d02e3ed5cc8",
      "parentUUID": "eb32a3ea-d0bc-4d34-a3ef-3c2da13de6d8",
      "skipped": false
    }
  ],
  "allFailures": [],
  "copyrightYear": 2016
}